idevice_backup/__init__.py
idevice_backup/cli.py
idevice_backup/commands/__init__.py
idevice_backup/commands/backup.py
idevice_backup/commands/extract.py
idevice_backup/commands/init.py
idevice_backup/commands/mount.py
idevice_backup/ios.py
idevice_backup/mime.py
idevice_backup/restic.py
idevice_backup/schema.py
idevice_backup/shell.py
idevice_backup/utils.py
idevice_backup-0.1.1.dist-info/LICENSE
idevice_backup-0.1.1.dist-info/METADATA
idevice_backup-0.1.1.dist-info/WHEEL
idevice_backup-0.1.1.dist-info/entry_points.txt
idevice_backup-0.1.1.dist-info/RECORD
